{"d8c505e45a0342d1f1291ba827195fda":{"statistic":{"failed":0,"broken":0,"skipped":0,"passed":2,"unknown":0,"total":2},"items":[{"uid":"9448c8454d6fdb2b","reportUrl":"https://chudinova.github.io/autotests-ui/18/#testresult/9448c8454d6fdb2b","status":"passed","time":{"start":1766384465682,"stop":1766384467457,"duration":1775}},{"uid":"9e4deeefc76ec9c4","reportUrl":"https://chudinova.github.io/autotests-ui/17/#testresult/9e4deeefc76ec9c4","status":"passed","time":{"start":1766322322788,"stop":1766322324259,"duration":1471}}]},"1ac91e93209424695453f5bd9839e52d":{"statistic":{"failed":0,"broken":0,"skipped":0,"passed":2,"unknown":0,"total":2},"items":[{"uid":"e78e16bf1356d763","reportUrl":"https://chudinova.github.io/autotests-ui/18/#testresult/e78e16bf1356d763","status":"passed","time":{"start":1766384479642,"stop":1766384483716,"duration":4074}},{"uid":"75241a4482cb676e","reportUrl":"https://chudinova.github.io/autotests-ui/17/#testresult/75241a4482cb676e","status":"passed","time":{"start":1766322339328,"stop":1766322343049,"duration":3721}}]},"c7080a775aca09562150dac0042516f8":{"statistic":{"failed":0,"broken":0,"skipped":0,"passed":2,"unknown":0,"total":2},"items":[{"uid":"4a79ca612a05a108","reportUrl":"https://chudinova.github.io/autotests-ui/18/#testresult/4a79ca612a05a108","status":"passed","time":{"start":1766384447294,"stop":1766384449324,"duration":2030}},{"uid":"387407a496adbdfe","reportUrl":"https://chudinova.github.io/autotests-ui/17/#testresult/387407a496adbdfe","status":"passed","time":{"start":1766322309503,"stop":1766322311479,"duration":1976}}]},"a3209611c392ebe11214033493164eb0":{"statistic":{"failed":0,"broken":0,"skipped":0,"passed":2,"unknown":0,"total":2},"items":[{"uid":"c6bca6d03b0a716","reportUrl":"https://chudinova.github.io/autotests-ui/18/#testresult/c6bca6d03b0a716","status":"passed","time":{"start":1766384455194,"stop":1766384457827,"duration":2633}},{"uid":"1e9b83d42d450517","reportUrl":"https://chudinova.github.io/autotests-ui/17/#testresult/1e9b83d42d450517","status":"passed","time":{"start":1766322316060,"stop":1766322318796,"duration":2736}}]},"12cc6f157e272bcd6a71994711b9d162":{"statistic":{"failed":0,"broken":0,"skipped":0,"passed":2,"unknown":0,"total":2},"items":[{"uid":"5b84ae5791a09155","reportUrl":"https://chudinova.github.io/autotests-ui/18/#testresult/5b84ae5791a09155","status":"passed","time":{"start":1766384458471,"stop":1766384464832,"duration":6361}},{"uid":"34147c4e8e1b996c","reportUrl":"https://chudinova.github.io/autotests-ui/17/#testresult/34147c4e8e1b996c","status":"passed","time":{"start":1766322316059,"stop":1766322322329,"duration":6270}}]},"265e1185a90c68ce202d3d3ffc79e8b1":{"statistic":{"failed":0,"broken":0,"skipped":0,"passed":2,"unknown":0,"total":2},"items":[{"uid":"b35c21c6a4a70171","reportUrl":"https://chudinova.github.io/autotests-ui/18/#testresult/b35c21c6a4a70171","status":"passed","time":{"start":1766384455199,"stop":1766384457833,"duration":2634}},{"uid":"6a1c764684480f05","reportUrl":"https://chudinova.github.io/autotests-ui/17/#testresult/6a1c764684480f05","status":"passed","time":{"start":1766322319557,"stop":1766322322307,"duration":2750}}]},"a142032bcd1bb8e6732fa953a15219eb":{"statistic":{"failed":0,"broken":0,"skipped":0,"passed":2,"unknown":0,"total":2},"items":[{"uid":"e5e4dbdd781fa9d3","reportUrl":"https://chudinova.github.io/autotests-ui/18/#testresult/e5e4dbdd781fa9d3","status":"passed","time":{"start":1766384449782,"stop":1766384451144,"duration":1362}},{"uid":"b427b128342d4966","reportUrl":"https://chudinova.github.io/autotests-ui/17/#testresult/b427b128342d4966","status":"passed","time":{"start":1766322311872,"stop":1766322313222,"duration":1350}}]},"5abda25e298351f613a6376db99131c2":{"statistic":{"failed":0,"broken":0,"skipped":0,"passed":2,"unknown":0,"total":2},"items":[{"uid":"6f88cbdac71721d1","reportUrl":"https://chudinova.github.io/autotests-ui/18/#testresult/6f88cbdac71721d1","status":"passed","time":{"start":1766384466659,"stop":1766384468552,"duration":1893}},{"uid":"5524dec0c8d5d0a9","reportUrl":"https://chudinova.github.io/autotests-ui/17/#testresult/5524dec0c8d5d0a9","status":"passed","time":{"start":1766322324770,"stop":1766322326470,"duration":1700}}]},"3887439a1115360d8f85c80c33cd5a34":{"statistic":{"failed":0,"broken":0,"skipped":0,"passed":2,"unknown":0,"total":2},"items":[{"uid":"c30337537cfa90fe","reportUrl":"https://chudinova.github.io/autotests-ui/18/#testresult/c30337537cfa90fe","status":"passed","time":{"start":1766384469354,"stop":1766384473363,"duration":4009}},{"uid":"55ba26fba7129d43","reportUrl":"https://chudinova.github.io/autotests-ui/17/#testresult/55ba26fba7129d43","status":"passed","time":{"start":1766322330373,"stop":1766322333520,"duration":3147}}]},"a17840214f48630f4981881e7ef1dde7":{"statistic":{"failed":0,"broken":0,"skipped":0,"passed":2,"unknown":0,"total":2},"items":[{"uid":"31b08c3b793bcf4d","reportUrl":"https://chudinova.github.io/autotests-ui/18/#testresult/31b08c3b793bcf4d","status":"passed","time":{"start":1766384487193,"stop":1766384489785,"duration":2592}},{"uid":"e6c7a974a5e86165","reportUrl":"https://chudinova.github.io/autotests-ui/17/#testresult/e6c7a974a5e86165","status":"passed","time":{"start":1766322349219,"stop":1766322351025,"duration":1806}}]},"18e044e52be5dd8e37ea09785c7c2820":{"statistic":{"failed":0,"broken":0,"skipped":0,"passed":2,"unknown":0,"total":2},"items":[{"uid":"47c5ca3a340f187b","reportUrl":"https://chudinova.github.io/autotests-ui/18/#testresult/47c5ca3a340f187b","status":"passed","time":{"start":1766384475588,"stop":1766384478992,"duration":3404}},{"uid":"8b844366d49195ea","reportUrl":"https://chudinova.github.io/autotests-ui/17/#testresult/8b844366d49195ea","status":"passed","time":{"start":1766322336029,"stop":1766322338720,"duration":2691}}]},"6f43f9e252940c24500c899b6fa77769":{"statistic":{"failed":0,"broken":0,"skipped":0,"passed":2,"unknown":0,"total":2},"items":[{"uid":"557d1fc4017be9fa","reportUrl":"https://chudinova.github.io/autotests-ui/18/#testresult/557d1fc4017be9fa","status":"passed","time":{"start":1766384461925,"stop":1766384465750,"duration":3825}},{"uid":"9c40a10158f46dbd","reportUrl":"https://chudinova.github.io/autotests-ui/17/#testresult/9c40a10158f46dbd","status":"passed","time":{"start":1766322325936,"stop":1766322329770,"duration":3834}}]},"212c3638a8ba79b2f0b7a6aac9a4bd69":{"statistic":{"failed":0,"broken":0,"skipped":0,"passed":2,"unknown":0,"total":2},"items":[{"uid":"15c243b04b5f0939","reportUrl":"https://chudinova.github.io/autotests-ui/18/#testresult/15c243b04b5f0939","status":"passed","time":{"start":1766384485193,"stop":1766384491393,"duration":6200}},{"uid":"5718a45f8ee4b0d0","reportUrl":"https://chudinova.github.io/autotests-ui/17/#testresult/5718a45f8ee4b0d0","status":"passed","time":{"start":1766322342081,"stop":1766322348399,"duration":6318}}]},"b1e74620ac2ff3c2d12112548a8bdd46":{"statistic":{"failed":0,"broken":0,"skipped":0,"passed":2,"unknown":0,"total":2},"items":[{"uid":"9fe4949b2b9aec26","reportUrl":"https://chudinova.github.io/autotests-ui/18/#testresult/9fe4949b2b9aec26","status":"passed","time":{"start":1766384447294,"stop":1766384449407,"duration":2113}},{"uid":"b596dc15b898b0ec","reportUrl":"https://chudinova.github.io/autotests-ui/17/#testresult/b596dc15b898b0ec","status":"passed","time":{"start":1766322309514,"stop":1766322311420,"duration":1906}}]},"9b3c0b79a80975e96ecb0d7f05e7ee29":{"statistic":{"failed":0,"broken":0,"skipped":0,"passed":2,"unknown":0,"total":2},"items":[{"uid":"c37e031a4987ccf2","reportUrl":"https://chudinova.github.io/autotests-ui/18/#testresult/c37e031a4987ccf2","status":"passed","time":{"start":1766384458463,"stop":1766384461476,"duration":3013}},{"uid":"bb5444c5b42d5c4e","reportUrl":"https://chudinova.github.io/autotests-ui/17/#testresult/bb5444c5b42d5c4e","status":"passed","time":{"start":1766322322908,"stop":1766322325670,"duration":2762}}]},"2665a68cc041e66979fef8ac01824763":{"statistic":{"failed":0,"broken":0,"skipped":0,"passed":2,"unknown":0,"total":2},"items":[{"uid":"8085457ae3a6d927","reportUrl":"https://chudinova.github.io/autotests-ui/18/#testresult/8085457ae3a6d927","status":"passed","time":{"start":1766384484462,"stop":1766384486463,"duration":2001}},{"uid":"7bc65afc6d450b4d","reportUrl":"https://chudinova.github.io/autotests-ui/17/#testresult/7bc65afc6d450b4d","status":"passed","time":{"start":1766322343639,"stop":1766322345819,"duration":2180}}]},"a2e4770448a4258081775cc84723f4ea":{"statistic":{"failed":0,"broken":0,"skipped":0,"passed":2,"unknown":0,"total":2},"items":[{"uid":"4fc649278f87b895","reportUrl":"https://chudinova.github.io/autotests-ui/18/#testresult/4fc649278f87b895","status":"passed","time":{"start":1766384479576,"stop":1766384484225,"duration":4649}},{"uid":"172dc125dffa239d","reportUrl":"https://chudinova.github.io/autotests-ui/17/#testresult/172dc125dffa239d","status":"passed","time":{"start":1766322336550,"stop":1766322340978,"duration":4428}}]},"e51f5dff523be524f1fabc3eaf9ce86d":{"statistic":{"failed":0,"broken":0,"skipped":0,"passed":2,"unknown":0,"total":2},"items":[{"uid":"511be9dea249abae","reportUrl":"https://chudinova.github.io/autotests-ui/18/#testresult/511be9dea249abae","status":"passed","time":{"start":1766384467773,"stop":1766384470061,"duration":2288}},{"uid":"183d0c8930a7252c","reportUrl":"https://chudinova.github.io/autotests-ui/17/#testresult/183d0c8930a7252c","status":"passed","time":{"start":1766322326780,"stop":1766322329007,"duration":2227}}]},"52819afde9c88e9964383828876debff":{"statistic":{"failed":0,"broken":0,"skipped":0,"passed":2,"unknown":0,"total":2},"items":[{"uid":"c95ec86cbc6b6aa8","reportUrl":"https://chudinova.github.io/autotests-ui/18/#testresult/c95ec86cbc6b6aa8","status":"passed","time":{"start":1766384472538,"stop":1766384474573,"duration":2035}},{"uid":"40ea5fe0f4e90ee4","reportUrl":"https://chudinova.github.io/autotests-ui/17/#testresult/40ea5fe0f4e90ee4","status":"passed","time":{"start":1766322331352,"stop":1766322332926,"duration":1574}}]},"38be389fb76f1f568eeaefbaafb2aa31":{"statistic":{"failed":0,"broken":0,"skipped":0,"passed":2,"unknown":0,"total":2},"items":[{"uid":"fa522763aa7cf6d6","reportUrl":"https://chudinova.github.io/autotests-ui/18/#testresult/fa522763aa7cf6d6","status":"passed","time":{"start":1766384476671,"stop":1766384478607,"duration":1936}},{"uid":"f1b41499aa965caf","reportUrl":"https://chudinova.github.io/autotests-ui/17/#testresult/f1b41499aa965caf","status":"passed","time":{"start":1766322334076,"stop":1766322335809,"duration":1733}}]}}